sero/VERSION
sero/__init__.py
sero/sero.py
sero-1.0.5.dist-info/LICENSE
sero-1.0.5.dist-info/METADATA
sero-1.0.5.dist-info/WHEEL
sero-1.0.5.dist-info/top_level.txt
sero-1.0.5.dist-info/RECORD
