Metadata-Version: 2.1
Name: sero
Version: 1.0.5
Summary: A simple module for concurrently running tasks.
Home-page: https://github.com/z3c0/sero
Author: z3c0
Author-email: z3c0@21337.tech
License: GPL-3.0
Keywords: pipeline
Platform: UNKNOWN
Classifier: License :: OSI Approved :: GNU General Public License v3 (GPLv3)
Requires-Python: >=3.9.1
